paracoord/__init__.py
paracoord/paracoord.py
paracoord-0.5.dist-info/LICENSE
paracoord-0.5.dist-info/METADATA
paracoord-0.5.dist-info/WHEEL
paracoord-0.5.dist-info/top_level.txt
paracoord-0.5.dist-info/RECORD
