Metadata-Version: 2.1
Name: paracoord
Version: 0.5
Summary: Parallel Coordinates plotting
Home-page: https://github.com/mancap314/paracoord
Author: Manuel Capel
Author-email: manuel.capel82@gmail.com
License: UNKNOWN
Platform: UNKNOWN
Classifier: Programming Language :: Python :: 3
Classifier: License :: OSI Approved :: MIT License
Classifier: Operating System :: OS Independent
